ydata_profile/__init__.py
ydata_profile/streamlit_app.py
ydata_profile-1.0.4.dist-info/licenses/LICENSE.md
ydata_profile-1.0.4.dist-info/METADATA
ydata_profile-1.0.4.dist-info/WHEEL
ydata_profile-1.0.4.dist-info/top_level.txt
ydata_profile-1.0.4.dist-info/RECORD
