Metadata-Version: 2.4
Name: ydata_profile
Version: 1.0.4
Author-email: Jordi Carrera Ventura <jordi.carrera.ventura@gmail.com>
Project-URL: GitHub repository, https://github.com/JordiCarreraVentura/ydata_profile
Classifier: Programming Language :: Python :: 3
Classifier: Operating System :: OS Independent
Classifier: Development Status :: 5 - Production/Stable
Classifier: Topic :: Scientific/Engineering :: Information Analysis
Requires-Python: <3.12,>=3.11
License-File: LICENSE.md
Requires-Dist: build==1.2.2.post1
Requires-Dist: midir
Requires-Dist: pandas==2.2.3
Requires-Dist: streamlit>=1.43.2
Requires-Dist: streamlit-ydata-profiling>=0.2.1
Requires-Dist: twine==5.1.1
Requires-Dist: ydata-profiling>=4.18.0
Dynamic: license-file
